muhidin/__init__.py
muhidin/core.py
upblib_muhidin-0.1.0.dist-info/licenses/LICENSE
upblib_muhidin-0.1.0.dist-info/METADATA
upblib_muhidin-0.1.0.dist-info/WHEEL
upblib_muhidin-0.1.0.dist-info/top_level.txt
upblib_muhidin-0.1.0.dist-info/RECORD
