Metadata-Version: 2.4
Name: upblib-muhidin
Version: 0.1.0
Summary: Pustaka Python contoh
Home-page: https://github.com/asepmuhidin
Author: Asep Muhidin
Author-email: asep.muhidin@pelitabangsa.ac.id
Classifier: Programming Language :: Python :: 3
Classifier: License :: OSI Approved :: MIT License
Requires-Python: >=3.6
License-File: LICENSE
Requires-Dist: pandas
Requires-Dist: matplotlib
Requires-Dist: seaborn
Dynamic: author
Dynamic: author-email
Dynamic: classifier
Dynamic: description-content-type
Dynamic: home-page
Dynamic: license-file
Dynamic: requires-dist
Dynamic: requires-python
Dynamic: summary
